{
  "user": [
    {
      "id": 1,
      "name": "Ariel",
      "password": "haslo",
      "isLogged": "false",
      "initialized": "false",
      "userEmail": "alek123@wp.pl",
      "surname": "false",
      "firm": "false",
      "placeWork": "false",
      "logo": "false",
      "coworkers": "false"
    },
    {
      "id": 2,
      "name": "Admin",
      "password": "haslo",
      "isLogged": "false",
      "initialized": "false",
      "userEmail": "alek123@wp.pl",
      "surname": "false",
      "firm": "false",
      "placeWork": "false",
      "logo": "false",
      "coworkers": "false"
    },
    {
      "name": "Tomek",
      "password": "tomek",
      "isLogged": "false",
      "initialized": "false",
      "userEmail": "alek123@wp.pl",
      "surname": "false",
      "firm": "false",
      "placeWork": "false",
      "logo": "false",
      "coworkers": "false",
      "id": 3
    },
    {
      "name": "Kasia",
      "password": "haslo",
      "isLogged": "false",
      "initialized": "false",
      "userEmail": "kasia123@wp.pl",
      "surname": "false",
      "firm": "false",
      "placeWork": "false",
      "logo": "false",
      "coworkers": "false",
      "id": 4
    },
    {
      "name": "Ariel12",
      "password": "haslo",
      "isLogged": "false",
      "initialized": "false",
      "userEmail": "alek123qasda23@wp.pl",
      "surname": "false",
      "firm": "false",
      "placeWork": "false",
      "logo": "false",
      "coworkers": "false",
      "id": 5
    },
    {
      "name": "test",
      "password": "$2a$10$wd4zZ10N4FrmQd1W4mux/O3zB3ZkhRWJrc1LDwPYaU4ew8uTi4ew.",
      "isLogged": "false",
      "initialized": "false",
      "userEmail": "sdfsd@sdf.pl",
      "surname": "false",
      "firm": "false",
      "placeWork": "false",
      "logo": "false",
      "coworkers": "false",
      "id": 6
    },
    {
      "name": "test",
      "password": "$2a$10$VRXv9Uqfh0DZkxJUyZ2Rr.wO9z8BO9Nl.4an94/R8.xdAMoPcdjpy",
      "isLogged": "false",
      "initialized": "false",
      "userEmail": "sdfsd@sdf.pl",
      "surname": "false",
      "firm": "false",
      "placeWork": "false",
      "logo": "false",
      "coworkers": "false",
      "id": 7
    },
    {
      "name": "kubus",
      "password": "$2a$10$hJe0dJvzvYj/ghzp2LmWaOK4XSXTfVyAXknzKdPYQPFLPRZj4kg5a",
      "isLogged": "false",
      "initialized": "false",
      "userEmail": "kubus123@wp.pl",
      "surname": "false",
      "firm": "false",
      "placeWork": "false",
      "logo": "false",
      "coworkers": "false",
      "id": 8
    }
  ],
  "orders": [
    {
      "id": 1,
      "author": "kasia123@wp.pl",
      "dateDeliveryAuthor:": [
        "2020-10-04",
        "2020-10-05",
        "2020-10-05"
      ],
      "delivery": "dostawa",
      "placeDelivery": "Brzegi, Kosowskiego 15",
      "firm": [
        "alek123@wp.pl",
        "en48@wp.pl"
      ],
      "status": "open",
      "elements": [
        {
          "fabric": "papa",
          "unit": "m2",
          "quantity": "10",
          "note": "konieczny jest atest"
        },
        {
          "fabric": "bloczki",
          "unit": "szt",
          "quantity": "50",
          "note": "konieczny rozładunek"
        }
      ],
      "dateAuthor": [
        "2020-08-27",
        "2020-08-29"
      ]
    },
    {
      "author": "alek123@wp.pl",
      "id": "2+AorderA+2",
      "dateDeliveryAuthor": [
        [],
        [],
        []
      ],
      "delivery": "jeśli jest adres to dostawa:",
      "placeDelivery": "",
      "firm": [
        "alek123@wp.pl",
        "alek1234@wp.pl",
        "alek12345@wp.pl"
      ],
      "status": "open",
      "elements": [
        {
          "fabric": "Czajnik",
          "unit": "szt",
          "quantity": "1",
          "note": "przezroczysty"
        },
        {
          "fabric": "parownik",
          "unit": "szt",
          "quantity": "2",
          "note": "stojacy"
        }
      ],
      "dateAuthor": [
        "2020-08-28T13:46:38.127Z",
        []
      ]
    },
    {
      "author": "alek123@wp.pl",
      "id": "2AorderA3",
      "dateDeliveryAuthor": [
        [],
        [],
        []
      ],
      "delivery": "jeśli jest adres to dostawa:",
      "placeDelivery": "",
      "firm": [
        "alek123@",
        "123",
        "sdasd",
        "sssa"
      ],
      "status": "open",
      "elements": [
        {
          "fabric": "asdasd",
          "unit": "asd",
          "quantity": "1",
          "note": "asdasd"
        }
      ],
      "dateAuthor": [
        "2020-08-28T14:01:04.069Z",
        []
      ]
    },
    {
      "author": "alek123@wp.pl",
      "id": "1AorderA4",
      "dateDeliveryAuthor": [
        [],
        [],
        []
      ],
      "delivery": "jeśli jest adres to dostawa:",
      "placeDelivery": "",
      "firm": [],
      "status": "open",
      "elements": [],
      "dateAuthor": [
        "2020-08-28T22:53:07.632Z",
        "2020-10-10"
      ]
    },
    {
      "author": "kubus123@wp.pl",
      "id": "8AorderA5",
      "dateDeliveryAuthor": [
        [],
        [],
        []
      ],
      "delivery": "jeśli jest adres to dostawa:",
      "placeDelivery": "",
      "firm": [],
      "status": "archive",
      "elements": [
        {
          "fabric": "datapicker",
          "unit": "szt",
          "quantity": "1",
          "note": "datapicker"
        }
      ],
      "dateAuthor": [
        "2020-08-29T09:02:23.866Z",
        []
      ]
    },
    {
      "author": "kubus123@wp.pl",
      "id": "8AorderA6",
      "dateDeliveryAuthor": [
        "2020-09-02T09:08:01.000Z",
        "2020-09-04T09:08:01.000Z",
        "2020-09-05T09:08:01.000Z"
      ],
      "delivery": "jeśli jest adres to dostawa:",
      "placeDelivery": "",
      "firm": [
        "alek123@wp.pl"
      ],
      "status": "archive",
      "elements": [
        {
          "fabric": "derulo",
          "unit": "szt",
          "quantity": "1",
          "note": "dzejson"
        }
      ],
      "dateAuthor": [
        "2020-08-29T09:08:41.896Z",
        "2020-08-29T09:08:01.491Z"
      ]
    },
    {
      "author": "kubus123@wp.pl",
      "id": "8AorderA7",
      "dateDeliveryAuthor": [
        "2020-09-03T07:10:08.000Z",
        "2020-09-04T07:10:08.000Z",
        "2020-09-05T07:10:08.000Z"
      ],
      "delivery": "jeśli jest adres to dostawa:",
      "placeDelivery": "dostarczenie",
      "firm": [
        "alek123@wp.pl",
        "alek1234@wp.pl",
        "alek12345@wp.pl"
      ],
      "status": "close",
      "elements": [
        {
          "fabric": "bloczki do murowania",
          "unit": "szt",
          "quantity": "500",
          "note": "porotherm",
          "price": 0,
          "priceAll": 0,
          "noteFirm": ""
        },
        {
          "fabric": "bloczki do ścian działowych ",
          "unit": "szt",
          "quantity": "29",
          "note": "lekkie",
          "price": 0,
          "priceAll": 0,
          "noteFirm": ""
        }
      ],
      "dateAuthor": [
        "2020-08-30T07:11:34.494Z",
        "2020-08-30T07:10:08.783Z"
      ]
    },
    {
      "author": "kubus123@wp.pl",
      "id": "8AorderA8",
      "dateDeliveryAuthor": [
        "2020-09-07T08:49:46.000Z",
        "2020-09-08T08:49:46.000Z",
        "2020-09-09T08:49:46.000Z"
      ],
      "delivery": "jeśli jest adres to dostawa:",
      "placeDelivery": "dostarczenie",
      "firm": [
        "alek123@wp.pl",
        "alek1234@wp.pl",
        "alek12345@wp.pl",
        "alek12@wp.pl"
      ],
      "status": "close",
      "elements": [
        {
          "fabric": "Zamówienie próbne",
          "unit": "szt",
          "quantity": "1",
          "note": "Do testowania aplikacji",
          "price": 0,
          "priceAll": 0,
          "noteFirm": ""
        },
        {
          "fabric": "Bloczki YTONG",
          "unit": "palet",
          "quantity": "4",
          "note": "Z rozładunkiem",
          "price": 0,
          "priceAll": 0,
          "noteFirm": ""
        },
        {
          "fabric": "Styropian AQUA 12cm",
          "unit": "m2",
          "quantity": "42",
          "note": "",
          "price": 0,
          "priceAll": 0,
          "noteFirm": ""
        },
        {
          "fabric": "Piana do styropianu",
          "unit": "szt",
          "quantity": "24",
          "note": "",
          "price": 0,
          "priceAll": 0,
          "noteFirm": ""
        },
        {
          "fabric": "kołki do styropianu 14cm",
          "unit": "szt",
          "quantity": "160",
          "note": "metalowe",
          "price": 0,
          "priceAll": 0,
          "noteFirm": ""
        }
      ],
      "dateAuthor": [
        "2020-08-30T08:52:56.450Z",
        "2020-09-04T08:49:46.000Z"
      ]
    },
    {
      "author": "kubus123@wp.pl",
      "id": "8AorderA9",
      "dateDeliveryAuthor": [
        "2020-08-30T09:03:50.106Z",
        "2020-08-30T09:03:50.106Z",
        "2020-08-30T09:03:50.106Z"
      ],
      "delivery": "jeśli jest adres to dostawa:",
      "placeDelivery": "Kraków bombonierki 12",
      "firm": [
        "wp.pl",
        "asdass",
        "dds"
      ],
      "status": "open",
      "elements": [
        {
          "fabric": "asdasd",
          "unit": "sss",
          "quantity": "asd",
          "note": "",
          "price": 0,
          "priceAll": 0,
          "noteFirm": ""
        },
        {
          "fabric": "aasd",
          "unit": "dsa",
          "quantity": "sdd",
          "note": "",
          "price": 0,
          "priceAll": 0,
          "noteFirm": ""
        }
      ],
      "dateAuthor": [
        "2020-08-30T09:04:13.300Z",
        "2020-08-30T09:03:50.106Z"
      ]
    }
  ],
  "ofert": [
    {
      "id": 1,
      "author": "kasia123@wp.pl",
      "dateDeliveryAuthor:": [
        "2020-10-04",
        "2020-10-05",
        "2020-10-05"
      ],
      "delivery": "dostawa",
      "placeDelivery": "Brzegi, Kosowskiego 15",
      "firm": [
        "alek123@wp.pl",
        "en48@wp.pl"
      ],
      "status": "open",
      "elements": [
        {
          "fabric": "papa",
          "unit": "m2",
          "quantity": "10",
          "note": "konieczny jest atest"
        },
        {
          "fabric": "bloczki",
          "unit": "szt",
          "quantity": "50",
          "note": "konieczny rozładunek"
        }
      ],
      "dateAuthor": [
        "2020-08-27",
        "2020-08-29"
      ]
    },
    {
      "author": "alek123@wp.pl",
      "id": "2AorderA3AofertA0",
      "dateDeliveryAuthor": [
        [],
        [],
        []
      ],
      "delivery": "jeśli jest adres to dostawa:",
      "placeDelivery": "",
      "firm": [
        "alek123@",
        "123",
        "sdasd",
        "sssa"
      ],
      "status": "open",
      "elements": [
        {
          "fabric": "asdasd",
          "unit": "asd",
          "quantity": "1",
          "note": "asdasd"
        }
      ],
      "dateAuthor": [
        "2020-08-28T14:01:04.069Z",
        []
      ]
    },
    {
      "author": "alek123@wp.pl",
      "id": "2AorderA3AofertA1",
      "dateDeliveryAuthor": [
        [],
        [],
        []
      ],
      "delivery": "jeśli jest adres to dostawa:",
      "placeDelivery": "",
      "firm": [
        "alek123@",
        "123",
        "sdasd",
        "sssa"
      ],
      "status": "open",
      "elements": [
        {
          "fabric": "asdasd",
          "unit": "asd",
          "quantity": "1",
          "note": "asdasd"
        }
      ],
      "dateAuthor": [
        "2020-08-28T14:01:04.069Z",
        []
      ]
    },
    {
      "author": "alek123@wp.pl",
      "id": "2AorderA3AofertA2",
      "dateDeliveryAuthor": [
        [],
        [],
        []
      ],
      "delivery": "jeśli jest adres to dostawa:",
      "placeDelivery": "",
      "firm": [
        "alek123@",
        "123",
        "sdasd",
        "sssa"
      ],
      "status": "open",
      "elements": [
        {
          "fabric": "asdasd",
          "unit": "asd",
          "quantity": "1",
          "note": "asdasd"
        }
      ],
      "dateAuthor": [
        "2020-08-28T14:01:04.069Z",
        []
      ]
    },
    {
      "author": "alek123@wp.pl",
      "id": "2AorderA3AofertA3",
      "dateDeliveryAuthor": [
        [],
        [],
        []
      ],
      "delivery": "jeśli jest adres to dostawa:",
      "placeDelivery": "",
      "firm": [
        "alek123@",
        "123",
        "sdasd",
        "sssa"
      ],
      "status": "open",
      "elements": [
        {
          "fabric": "asdasd",
          "unit": "asd",
          "quantity": "1",
          "note": "asdasd"
        }
      ],
      "dateAuthor": [
        "2020-08-28T14:01:04.069Z",
        []
      ]
    },
    {
      "author": "kubus123@wp.pl",
      "id": "8AorderA6AofertA0",
      "dateDeliveryAuthor": [
        "2020-09-02T09:08:01.000Z",
        "2020-09-04T09:08:01.000Z",
        "2020-09-05T09:08:01.000Z"
      ],
      "delivery": "jeśli jest adres to dostawa:",
      "placeDelivery": "",
      "firm": [
        "alek123@wp.pl"
      ],
      "status": "open",
      "elements": [
        {
          "fabric": "derulo",
          "unit": "szt",
          "quantity": "1",
          "note": "dzejson"
        }
      ],
      "dateAuthor": [
        "2020-08-29T09:08:41.896Z",
        "2020-08-29T09:08:01.491Z"
      ]
    },
    {
      "author": "kubus123@wp.pl",
      "id": "8AorderA7AofertA0",
      "dateDeliveryAuthor": [
        "2020-09-03T07:10:08.000Z",
        "2020-09-04T07:10:08.000Z",
        "2020-09-05T07:10:08.000Z"
      ],
      "delivery": "jeśli jest adres to dostawa:",
      "placeDelivery": "dostarczenie",
      "firm": [
        "alek123@wp.pl",
        "alek1234@wp.pl",
        "alek12345@wp.pl"
      ],
      "status": "open",
      "elements": [
        {
          "fabric": "bloczki do murowania",
          "unit": "szt",
          "quantity": "500",
          "note": "porotherm",
          "price": 0,
          "priceAll": 0,
          "noteFirm": ""
        },
        {
          "fabric": "bloczki do ścian działowych ",
          "unit": "szt",
          "quantity": "29",
          "note": "lekkie",
          "price": 0,
          "priceAll": 0,
          "noteFirm": ""
        }
      ],
      "dateAuthor": [
        "2020-08-30T07:11:34.494Z",
        "2020-08-30T07:10:08.783Z"
      ]
    },
    {
      "author": "kubus123@wp.pl",
      "id": "8AorderA7AofertA1",
      "dateDeliveryAuthor": [
        "2020-09-03T07:10:08.000Z",
        "2020-09-04T07:10:08.000Z",
        "2020-09-05T07:10:08.000Z"
      ],
      "delivery": "jeśli jest adres to dostawa:",
      "placeDelivery": "dostarczenie",
      "firm": [
        "alek123@wp.pl",
        "alek1234@wp.pl",
        "alek12345@wp.pl"
      ],
      "status": "open",
      "elements": [
        {
          "fabric": "bloczki do murowania",
          "unit": "szt",
          "quantity": "500",
          "note": "porotherm",
          "price": 0,
          "priceAll": 0,
          "noteFirm": ""
        },
        {
          "fabric": "bloczki do ścian działowych ",
          "unit": "szt",
          "quantity": "29",
          "note": "lekkie",
          "price": 0,
          "priceAll": 0,
          "noteFirm": ""
        }
      ],
      "dateAuthor": [
        "2020-08-30T07:11:34.494Z",
        "2020-08-30T07:10:08.783Z"
      ]
    },
    {
      "author": "kubus123@wp.pl",
      "id": "8AorderA7AofertA2",
      "dateDeliveryAuthor": [
        "2020-09-03T07:10:08.000Z",
        "2020-09-04T07:10:08.000Z",
        "2020-09-05T07:10:08.000Z"
      ],
      "delivery": "jeśli jest adres to dostawa:",
      "placeDelivery": "dostarczenie",
      "firm": [
        "alek123@wp.pl",
        "alek1234@wp.pl",
        "alek12345@wp.pl"
      ],
      "status": "open",
      "elements": [
        {
          "fabric": "bloczki do murowania",
          "unit": "szt",
          "quantity": "500",
          "note": "porotherm",
          "price": 0,
          "priceAll": 0,
          "noteFirm": ""
        },
        {
          "fabric": "bloczki do ścian działowych ",
          "unit": "szt",
          "quantity": "29",
          "note": "lekkie",
          "price": 0,
          "priceAll": 0,
          "noteFirm": ""
        }
      ],
      "dateAuthor": [
        "2020-08-30T07:11:34.494Z",
        "2020-08-30T07:10:08.783Z"
      ]
    },
    {
      "author": "kubus123@wp.pl",
      "id": "8AorderA8AofertA0",
      "dateDeliveryAuthor": [
        "2020-09-07T08:49:46.000Z",
        "2020-09-08T08:49:46.000Z",
        "2020-09-09T08:49:46.000Z"
      ],
      "delivery": "jeśli jest adres to dostawa:",
      "placeDelivery": "dostarczenie",
      "firm": [
        "alek123@wp.pl",
        "alek1234@wp.pl",
        "alek12345@wp.pl",
        "alek12@wp.pl"
      ],
      "status": "open",
      "elements": [
        {
          "fabric": "Zamówienie próbne",
          "unit": "szt",
          "quantity": "1",
          "note": "Do testowania aplikacji",
          "price": 0,
          "priceAll": 0,
          "noteFirm": ""
        },
        {
          "fabric": "Bloczki YTONG",
          "unit": "palet",
          "quantity": "4",
          "note": "Z rozładunkiem",
          "price": 0,
          "priceAll": 0,
          "noteFirm": ""
        },
        {
          "fabric": "Styropian AQUA 12cm",
          "unit": "m2",
          "quantity": "42",
          "note": "",
          "price": 0,
          "priceAll": 0,
          "noteFirm": ""
        },
        {
          "fabric": "Piana do styropianu",
          "unit": "szt",
          "quantity": "24",
          "note": "",
          "price": 0,
          "priceAll": 0,
          "noteFirm": ""
        },
        {
          "fabric": "kołki do styropianu 14cm",
          "unit": "szt",
          "quantity": "160",
          "note": "metalowe",
          "price": 0,
          "priceAll": 0,
          "noteFirm": ""
        }
      ],
      "dateAuthor": [
        "2020-08-30T08:52:56.450Z",
        "2020-09-04T08:49:46.000Z"
      ]
    },
    {
      "author": "kubus123@wp.pl",
      "id": "8AorderA8AofertA1",
      "dateDeliveryAuthor": [
        "2020-09-07T08:49:46.000Z",
        "2020-09-08T08:49:46.000Z",
        "2020-09-09T08:49:46.000Z"
      ],
      "delivery": "jeśli jest adres to dostawa:",
      "placeDelivery": "dostarczenie",
      "firm": [
        "alek123@wp.pl",
        "alek1234@wp.pl",
        "alek12345@wp.pl",
        "alek12@wp.pl"
      ],
      "status": "open",
      "elements": [
        {
          "fabric": "Zamówienie próbne",
          "unit": "szt",
          "quantity": "1",
          "note": "Do testowania aplikacji",
          "price": "12",
          "priceAll": "12",
          "noteFirm": ""
        },
        {
          "fabric": "Bloczki YTONG",
          "unit": "palet",
          "quantity": "4",
          "note": "Z rozładunkiem",
          "price": "12",
          "priceAll": "rozładunek po waszej stronie",
          "noteFirm": ""
        },
        {
          "fabric": "Styropian AQUA 12cm",
          "unit": "m2",
          "quantity": "42",
          "note": "",
          "price": "134",
          "priceAll": "12",
          "noteFirm": ""
        },
        {
          "fabric": "Piana do styropianu",
          "unit": "szt",
          "quantity": "24",
          "note": "",
          "price": "12",
          "priceAll": "12",
          "noteFirm": ""
        },
        {
          "fabric": "kołki do styropianu 14cm",
          "unit": "szt",
          "quantity": "160",
          "note": "metalowe",
          "price": "124",
          "priceAll": "12",
          "noteFirm": ""
        }
      ],
      "dateAuthor": [
        "2020-08-30T08:52:56.450Z",
        "2020-09-04T08:49:46.000Z"
      ]
    },
    {
      "author": "kubus123@wp.pl",
      "id": "8AorderA8AofertA2",
      "dateDeliveryAuthor": [
        "2020-09-07T08:49:46.000Z",
        "2020-09-08T08:49:46.000Z",
        "2020-09-09T08:49:46.000Z"
      ],
      "delivery": "jeśli jest adres to dostawa:",
      "placeDelivery": "dostarczenie",
      "firm": [
        "alek123@wp.pl",
        "alek1234@wp.pl",
        "alek12345@wp.pl",
        "alek12@wp.pl"
      ],
      "status": "close",
      "elements": [
        {
          "fabric": "Zamówienie próbne",
          "unit": "szt",
          "quantity": "1",
          "note": "Do testowania aplikacji",
          "price": "12",
          "priceAll": "12",
          "noteFirm": ""
        },
        {
          "fabric": "Bloczki YTONG",
          "unit": "palet",
          "quantity": "4",
          "note": "Z rozładunkiem",
          "price": "12",
          "priceAll": "12",
          "noteFirm": ""
        },
        {
          "fabric": "Styropian AQUA 12cm",
          "unit": "m2",
          "quantity": "42",
          "note": "",
          "price": "12",
          "priceAll": "12",
          "noteFirm": ""
        },
        {
          "fabric": "Piana do styropianu",
          "unit": "szt",
          "quantity": "24",
          "note": "",
          "price": "12",
          "priceAll": "12",
          "noteFirm": ""
        },
        {
          "fabric": "kołki do styropianu 14cm",
          "unit": "szt",
          "quantity": "160",
          "note": "metalowe",
          "price": "2332",
          "priceAll": "221",
          "noteFirm": ""
        }
      ],
      "dateAuthor": [
        "2020-08-30T08:52:56.450Z",
        "2020-09-04T08:49:46.000Z"
      ]
    },
    {
      "author": "kubus123@wp.pl",
      "id": "8AorderA8AofertA3",
      "dateDeliveryAuthor": [
        "2020-09-07T08:49:46.000Z",
        "2020-09-08T08:49:46.000Z",
        "2020-09-09T08:49:46.000Z"
      ],
      "delivery": "dostarczenie",
      "placeDelivery": "Brzesko pasikonika 123",
      "firm": [
        "alek123@wp.pl",
        "alek1234@wp.pl",
        "alek12345@wp.pl",
        "alek12@wp.pl"
      ],
      "status": "open",
      "elements": [
        {
          "fabric": "Zamówienie próbne",
          "unit": "szt",
          "quantity": "1",
          "note": "Do testowania aplikacji",
          "price": "11",
          "priceAll": "16",
          "noteFirm": ""
        },
        {
          "fabric": "Bloczki YTONG",
          "unit": "palet",
          "quantity": "4",
          "note": "Z rozładunkiem",
          "price": "12",
          "priceAll": "Brak rozładunku",
          "noteFirm": ""
        },
        {
          "fabric": "Styropian AQUA 12cm",
          "unit": "m2",
          "quantity": "42",
          "note": "",
          "price": "13",
          "priceAll": "18",
          "noteFirm": ""
        },
        {
          "fabric": "Piana do styropianu",
          "unit": "szt",
          "quantity": "24",
          "note": "",
          "price": "14",
          "priceAll": "ale tylko ogniowa",
          "noteFirm": ""
        },
        {
          "fabric": "kołki do styropianu 14cm",
          "unit": "szt",
          "quantity": "160",
          "note": "metalowe",
          "price": "15",
          "priceAll": "20",
          "noteFirm": ""
        }
      ],
      "dateAuthor": [
        "2020-08-30T08:52:56.450Z",
        "2020-09-04T08:49:46.000Z"
      ]
    },
    {
      "author": "kubus123@wp.pl",
      "id": "8AorderA9AofertA0",
      "dateDeliveryAuthor": [
        "2020-08-30T09:03:50.106Z",
        "2020-08-30T09:03:50.106Z",
        "2020-08-30T09:03:50.106Z"
      ],
      "delivery": "jeśli jest adres to dostawa:",
      "placeDelivery": "Kraków bombonierki 12",
      "firm": [
        "wp.pl",
        "asdass",
        "dds"
      ],
      "status": "open",
      "elements": [
        {
          "fabric": "asdasd",
          "unit": "sss",
          "quantity": "asd",
          "note": "",
          "price": 0,
          "priceAll": 0,
          "noteFirm": ""
        },
        {
          "fabric": "aasd",
          "unit": "dsa",
          "quantity": "sdd",
          "note": "",
          "price": 0,
          "priceAll": 0,
          "noteFirm": ""
        }
      ],
      "dateAuthor": [
        "2020-08-30T09:04:13.300Z",
        "2020-08-30T09:03:50.106Z"
      ]
    },
    {
      "author": "kubus123@wp.pl",
      "id": "8AorderA9AofertA1",
      "dateDeliveryAuthor": [
        "2020-08-30T09:03:50.106Z",
        "2020-08-30T09:03:50.106Z",
        "2020-08-30T09:03:50.106Z"
      ],
      "delivery": "jeśli jest adres to dostawa:",
      "placeDelivery": "Kraków bombonierki 12",
      "firm": [
        "wp.pl",
        "asdass",
        "dds"
      ],
      "status": "open",
      "elements": [
        {
          "fabric": "asdasd",
          "unit": "sss",
          "quantity": "asd",
          "note": "",
          "price": 0,
          "priceAll": 0,
          "noteFirm": ""
        },
        {
          "fabric": "aasd",
          "unit": "dsa",
          "quantity": "sdd",
          "note": "",
          "price": 0,
          "priceAll": 0,
          "noteFirm": ""
        }
      ],
      "dateAuthor": [
        "2020-08-30T09:04:13.300Z",
        "2020-08-30T09:03:50.106Z"
      ]
    },
    {
      "author": "kubus123@wp.pl",
      "id": "8AorderA9AofertA2",
      "dateDeliveryAuthor": [
        "2020-08-30T09:03:50.106Z",
        "2020-08-30T09:03:50.106Z",
        "2020-08-30T09:03:50.106Z"
      ],
      "delivery": "dostawa",
      "placeDelivery": "Kraków bombonierki 12",
      "firm": [
        "wp.pl",
        "asdass",
        "dds"
      ],
      "status": "open",
      "elements": [
        {
          "fabric": "asdasd",
          "unit": "sss",
          "quantity": "asd",
          "note": "",
          "price": 0,
          "priceAll": 0,
          "noteFirm": ""
        },
        {
          "fabric": "aasd",
          "unit": "dsa",
          "quantity": "sdd",
          "note": "",
          "price": 0,
          "priceAll": 0,
          "noteFirm": ""
        }
      ],
      "dateAuthor": [
        "2020-08-30T09:04:13.300Z",
        "2020-08-30T09:03:50.106Z"
      ]
    }
  ]
}